tecombine-0.2.7.1.data/purelib/tecombine/__init__.py
tecombine-0.2.7.1.data/purelib/tecombine/_libcombine.so
tecombine-0.2.7.1.data/purelib/tecombine/libcombine.py
tecombine-0.2.7.1.dist-info/METADATA
tecombine-0.2.7.1.dist-info/WHEEL
tecombine-0.2.7.1.dist-info/top_level.txt
tecombine-0.2.7.1.dist-info/RECORD
