Metadata-Version: 2.1
Name: tecombine
Version: 0.2.7.1
Summary: A library for working with COMBINE archives
Home-page: https://github.com/sbmlteam/libCombine
Author: Frank Bergmann, Kyle Medley (packaging)
Author-email: UNKNOWN
License: UNKNOWN
Platform: UNKNOWN
Classifier: Intended Audience :: Science/Research
Classifier: Operating System :: MacOS :: MacOS X
Classifier: Operating System :: Microsoft :: Windows
Classifier: Operating System :: POSIX
Classifier: Programming Language :: C++
